fpbase/__init__.py
fpbase/_fetch.py
fpbase/_graphql.py
fpbase/models.py
fpbase/py.typed
fpbase-0.1.2.dist-info/METADATA
fpbase-0.1.2.dist-info/WHEEL
fpbase-0.1.2.dist-info/licenses/LICENSE
fpbase-0.1.2.dist-info/RECORD
